{"took":2,"timed_out":false,"_shards":{"total":5,"successful":5,"skipped":0,"failed":0},"hits":{"total":280830,"max_score":1.0,"hits":[{"_index":"portstats","_type":"doc","_id":"Y0cc02UBy9OTDQ7b_Jez","_score":1.0,"_source":{"port":5,"bytesReceived":0,"bytesSent":0,"packetsReceived":0,"packetsSent":0,"packetsRxDropped":0,"packetsTxDropped":0,"packetsRxErrors":0,"packetsTxErrors":-1,"deviceName":"cicada","deviceId":"of:0000cc37ab772c80","host":"cicada","@timestamp":"2018-09-13T13:26:56Z"}},{"_index":"portstats","_type":"doc","_id":"ZEcc02UBy9OTDQ7b_Je4","_score":1.0,"_source":{"port":6,"bytesReceived":0,"bytesSent":0,"packetsReceived":0,"packetsSent":0,"packetsRxDropped":0,"packetsTxDropped":0,"packetsRxErrors":0,"packetsTxErrors":-1,"deviceName":"cicada","deviceId":"of:0000cc37ab772c80","host":"cicada","@timestamp":"2018-09-13T13:26:56Z"}},{"_index":"portstats","_type":"doc","_id":"aUcc02UBy9OTDQ7b_JfT","_score":1.0,"_source":{"port":11,"bytesReceived":0,"bytesSent":0,"packetsReceived":0,"packetsSent":0,"packetsRxDropped":0,"packetsTxDropped":0,"packetsRxErrors":0,"packetsTxErrors":-1,"deviceName":"cicada","deviceId":"of:0000cc37ab772c80","host":"cicada","@timestamp":"2018-09-13T13:26:56Z"}},{"_index":"portstats","_type":"doc","_id":"akcc02UBy9OTDQ7b_JfX","_score":1.0,"_source":{"port":12,"bytesReceived":0,"bytesSent":0,"packetsReceived":0,"packetsSent":0,"packetsRxDropped":0,"packetsTxDropped":0,"packetsRxErrors":0,"packetsTxErrors":-1,"deviceName":"cicada","deviceId":"of:0000cc37ab772c80","host":"cicada","@timestamp":"2018-09-13T13:26:56Z"}},{"_index":"portstats","_type":"doc","_id":"a0cc02UBy9OTDQ7b_Jfc","_score":1.0,"_source":{"port":13,"bytesReceived":0,"bytesSent":0,"packetsReceived":0,"packetsSent":0,"packetsRxDropped":0,"packetsTxDropped":0,"packetsRxErrors":0,"packetsTxErrors":-1,"deviceName":"cicada","deviceId":"of:0000cc37ab772c80","host":"cicada","@timestamp":"2018-09-13T13:26:56Z"}},{"_index":"portstats","_type":"doc","_id":"cUcc02UBy9OTDQ7b_Jf-","_score":1.0,"_source":{"port":19,"bytesReceived":0,"bytesSent":0,"packetsReceived":0,"packetsSent":0,"packetsRxDropped":0,"packetsTxDropped":0,"packetsRxErrors":0,"packetsTxErrors":-1,"deviceName":"cicada","deviceId":"of:0000cc37ab772c80","host":"cicada","@timestamp":"2018-09-13T13:26:56Z"}},{"_index":"portstats","_type":"doc","_id":"c0cc02UBy9OTDQ7b_ZcH","_score":1.0,"_source":{"port":21,"bytesReceived":0,"bytesSent":0,"packetsReceived":0,"packetsSent":0,"packetsRxDropped":0,"packetsTxDropped":0,"packetsRxErrors":0,"packetsTxErrors":-1,"deviceName":"cicada","deviceId":"of:0000cc37ab772c80","host":"cicada","@timestamp":"2018-09-13T13:26:56Z"}},{"_index":"portstats","_type":"doc","_id":"d0cc02UBy9OTDQ7b_Zcf","_score":1.0,"_source":{"port":25,"bytesReceived":0,"bytesSent":0,"packetsReceived":0,"packetsSent":0,"packetsRxDropped":0,"packetsTxDropped":0,"packetsRxErrors":0,"packetsTxErrors":-1,"deviceName":"cicada","deviceId":"of:0000cc37ab772c80","host":"cicada","@timestamp":"2018-09-13T13:26:56Z"}},{"_index":"portstats","_type":"doc","_id":"eUcc02UBy9OTDQ7b_Zcp","_score":1.0,"_source":{"port":27,"bytesReceived":0,"bytesSent":0,"packetsReceived":0,"packetsSent":0,"packetsRxDropped":0,"packetsTxDropped":0,"packetsRxErrors":0,"packetsTxErrors":-1,"deviceName":"cicada","deviceId":"of:0000cc37ab772c80","host":"cicada","@timestamp":"2018-09-13T13:26:56Z"}},{"_index":"portstats","_type":"doc","_id":"JUcc02UBy9OTDQ7bh5NB","_score":1.0,"_source":{"port":6,"bytesReceived":0,"bytesSent":0,"packetsReceived":0,"packetsSent":0,"packetsRxDropped":0,"packetsTxDropped":0,"packetsRxErrors":0,"packetsTxErrors":-1,"deviceName":"cicada","deviceId":"of:0000cc37ab772c80","host":"cicada","@timestamp":"2018-09-13T13:26:26Z"}}]}}